hundate/__init__.py
hundate/ezdate.py
hundate/ezhelper.py
hundate-1.0.4.dist-info/METADATA
hundate-1.0.4.dist-info/WHEEL
hundate-1.0.4.dist-info/top_level.txt
hundate-1.0.4.dist-info/RECORD
