Metadata-Version: 2.1
Name: hundate
Version: 1.0.4
Summary: NLP modul for hungarian date-entity recognition and translation to specific date values
Home-page: https://github.com/COREtxt/hundate-core
Author: Emődy Zsolt
Author-email: diszkurziv@gmail.com
License: UNKNOWN
Project-URL: Bug Tracker, https://github.com/COREtxt/hundate-core/issues
Platform: UNKNOWN
Classifier: Programming Language :: Python :: 3
Classifier: Environment :: Console
Classifier: Intended Audience :: Science/Research
Classifier: License :: OSI Approved :: MIT License
Classifier: Operating System :: OS Independent
Requires-Python: >=3.7
Requires-Dist: numpy (>=1.21.5)
Requires-Dist: python-dateutil (>=2.8.1)
